df_grouping_utils/__init__.py
df_grouping_utils/multiple_df_groupby.py
df_grouping_utils-0.0.1.dist-info/METADATA
df_grouping_utils-0.0.1.dist-info/WHEEL
df_grouping_utils-0.0.1.dist-info/licence.txt
df_grouping_utils-0.0.1.dist-info/top_level.txt
df_grouping_utils-0.0.1.dist-info/RECORD
