Metadata-Version: 2.1
Name: df-grouping-utils
Version: 0.0.1
Summary: Dataframe extention package.
Home-page: https://github.com/Ruairi-osul/df-grouping-utils
Author: Ruairi O'Sullivan
Author-email: ruairi.osullivan.work@gmail.com
License: GNU GPLv3
Project-URL: Source, https://github.com/Ruairi-osul/df-grouping-utils
Keywords: data-analysis
Platform: UNKNOWN
Requires-Python: >=3.6
License-File: licence.txt
Requires-Dist: pandas
